flyalert/FlyAlert.py
flyalert/__init__.py
flyalert-2.0.0.dist-info/licenses/LICENSE
flyalert-2.0.0.dist-info/METADATA
flyalert-2.0.0.dist-info/WHEEL
flyalert-2.0.0.dist-info/top_level.txt
flyalert-2.0.0.dist-info/RECORD
