Metadata-Version: 2.4
Name: flyalert
Version: 2.0.0
Summary: Custom animated alerts and dialogs for PyQt5.
Home-page: https://github.com/Amirhossein871/flyalert
Author: Amirhossein Bohlouli
Author-email: bohloli.amirh@gmail.com
Classifier: Programming Language :: Python :: 3
Classifier: License :: OSI Approved :: MIT License
Classifier: Operating System :: OS Independent
Requires-Python: >=3.6
License-File: LICENSE
Requires-Dist: PyQt5
Dynamic: author
Dynamic: author-email
Dynamic: classifier
Dynamic: description
Dynamic: description-content-type
Dynamic: home-page
Dynamic: license-file
Dynamic: requires-dist
Dynamic: requires-python
Dynamic: summary
